tonic_textual/__init__.py
tonic_textual/audio_api.py
tonic_textual/classes/SolarCsvConfig.py
tonic_textual/classes/__init__.py
tonic_textual/classes/audio/__init__.py
tonic_textual/classes/audio/redact_audio_responses.py
tonic_textual/classes/audio/redacted_transcription_result.py
tonic_textual/classes/common_api_responses/__init__.py
tonic_textual/classes/common_api_responses/base_file.py
tonic_textual/classes/common_api_responses/label_custom_list.py
tonic_textual/classes/common_api_responses/pii_occurences/__init__.py
tonic_textual/classes/common_api_responses/pii_occurences/ner_redaction_api_model.py
tonic_textual/classes/common_api_responses/pii_occurences/ner_redaction_page_api_model.py
tonic_textual/classes/common_api_responses/pii_occurences/paginated_pii_occurrence_response.py
tonic_textual/classes/common_api_responses/pii_occurences/pii_occurrence_response.py
tonic_textual/classes/common_api_responses/replacement.py
tonic_textual/classes/common_api_responses/single_detection_result.py
tonic_textual/classes/dataset.py
tonic_textual/classes/datasetfile.py
tonic_textual/classes/enums/aws_credentials_source.py
tonic_textual/classes/enums/docx_header_footer_type.py
tonic_textual/classes/enums/file_redaction_policies.py
tonic_textual/classes/enums/file_source.py
tonic_textual/classes/enums/file_type.py
tonic_textual/classes/enums/object_storage_type.py
tonic_textual/classes/enums/pdf_content_type.py
tonic_textual/classes/enums/pdf_table_cell_type.py
tonic_textual/classes/file_content/base_document.py
tonic_textual/classes/file_content/content.py
tonic_textual/classes/file_content/csv_document.py
tonic_textual/classes/file_content/docx_document.py
tonic_textual/classes/file_content/email_document.py
tonic_textual/classes/file_content/pdf_document.py
tonic_textual/classes/file_content/raw_document.py
tonic_textual/classes/file_content/xlsx_document.py
tonic_textual/classes/generator_metadata/age_shift_metadata.py
tonic_textual-3.15.2.dist-info/METADATA
tonic_textual-3.15.2.dist-info/WHEEL
tonic_textual-3.15.2.dist-info/licenses/LICENSE
tonic_textual-3.15.2.dist-info/RECORD
