Metadata-Version: 2.4
Name: tonic-textual
Version: 3.15.2
Summary: Wrappers around the Tonic Textual API
License: MIT
License-File: LICENSE
Keywords: tonic.ai,tonic,tonic textual
Author: Adam Kamor
Author-email: adam@tonic.ai
Requires-Python: >=3.9,<4.0
Classifier: License :: OSI Approved :: MIT License
Classifier: Operating System :: OS Independent
Classifier: Programming Language :: Python :: 3
Classifier: Programming Language :: Python :: 3.9
Classifier: Programming Language :: Python :: 3.10
Classifier: Programming Language :: Python :: 3.11
Classifier: Programming Language :: Python :: 3.12
Classifier: Programming Language :: Python :: 3.13
Classifier: Programming Language :: Python :: 3.14
Requires-Dist: more-itertools (>=10.2.0,<11.0.0)
Requires-Dist: requests (>=2.32.3,<3.0.0)
Requires-Dist: tqdm (>=4.67.1,<5.0.0)
Project-URL: Homepage, https://www.tonic.ai/
